yandex_api_client/__init__.py
yandex_api_client/api/__init__.py
yandex_api_client/api/bids_api.py
yandex_api_client/api/business_offer_mappings_api.py
yandex_api_client/api/campaigns_api.py
yandex_api_client/api/categories_api.py
yandex_api_client/api/chats_api.py
yandex_api_client/api/content_api.py
yandex_api_client/api/dbs_api.py
yandex_api_client/api/delivery_services_api.py
yandex_api_client/api/express_api.py
yandex_api_client/api/fbs_api.py
yandex_api_client/api/fby_api.py
yandex_api_client/api/feed_categories_api.py
yandex_api_client/api/feedbacks_api.py
yandex_api_client/api/feeds_api.py
yandex_api_client/api/goods_stats_api.py
yandex_api_client/api/hidden_offers_api.py
yandex_api_client/api/models_api.py
yandex_api_client/api/offer_mappings_api.py
yandex_api_client/api/offers_api.py
yandex_api_client/api/order_business_information_api.py
yandex_api_client/api/order_delivery_api.py
yandex_api_client/api/order_labels_api.py
yandex_api_client/api/orders_api.py
yandex_api_client/api/orders_stats_api.py
yandex_api_client/api/outlet_licenses_api.py
yandex_api_client/api/outlets_api.py
yandex_api_client/api/price_quarantine_api.py
yandex_api_client/api/prices_api.py
yandex_api_client/api/regions_api.py
yandex_api_client/api/reports_api.py
yandex_api_client/api/returns_api.py
yandex_api_client/api/shipments_api.py
yandex_api_client/api/stocks_api.py
yandex_api_client/api/tariffs_api.py
yandex_api_client/api/warehouses_api.py
yandex_api_client/api_client.py
yandex_api_client/api_response.py
yandex_api_client/configuration.py
yandex_api_client/exceptions.py
yandex_api_client/models/__init__.py
yandex_api_client/models/accept_order_cancellation_request.py
yandex_api_client/models/add_hidden_offers_request.py
yandex_api_client/models/add_offers_to_archive_dto.py
yandex_api_client/models/add_offers_to_archive_error_dto.py
yandex_api_client/models/add_offers_to_archive_error_type.py
yandex_api_client/models/add_offers_to_archive_request.py
yandex_api_client-0.0.2.dist-info/METADATA
yandex_api_client-0.0.2.dist-info/WHEEL
yandex_api_client-0.0.2.dist-info/RECORD
